flanabot/connect_4_frontend.py
flanabot/constants.py
flanabot/main.py
flanabot/bots/__init__.py
flanabot/bots/connect_4_bot.py
flanabot/bots/flana_bot.py
flanabot/bots/flana_disc_bot.py
flanabot/bots/flana_tele_bot.py
flanabot/bots/penalty_bot.py
flanabot/bots/poll_bot.py
flanabot/bots/scraper_bot.py
flanabot/bots/ubereats_bot.py
flanabot/bots/weather_bot.py
flanabot/models/__init__.py
flanabot/models/bot_action.py
flanabot/models/chat.py
flanabot/models/enums.py
flanabot/models/message.py
flanabot/models/player.py
flanabot/models/punishment.py
flanabot/models/weather_chart.py
flanabot/resources/mucho_texto.png
flanabot-1.5.2.dist-info/LICENSE
flanabot-1.5.2.dist-info/METADATA
flanabot-1.5.2.dist-info/WHEEL
flanabot-1.5.2.dist-info/top_level.txt
flanabot-1.5.2.dist-info/RECORD
