Metadata-Version: 2.1
Name: flanabot
Version: 1.5.2
Summary: Bot based on https://github.com/AlberLC/multibot to manage Discord, Telegram and Twitch chats, moderate them and add functionalities.
Home-page: https://github.com/AlberLC/flanabot
Author: AlberLC
Project-URL: Bug Tracker, https://github.com/AlberLC/flanabot/issues
Classifier: Programming Language :: Python :: 3.10
Classifier: License :: OSI Approved :: MIT License
Classifier: Operating System :: OS Independent
Requires-Python: >=3.10
License-File: LICENSE
Requires-Dist: flanaapis
Requires-Dist: flanautils
Requires-Dist: multibot
Requires-Dist: plotly
Requires-Dist: pycairo
Requires-Dist: pytz
